memez/__init__.py
memez/getMeme.py
memez-0.0.5.dist-info/METADATA
memez-0.0.5.dist-info/WHEEL
memez-0.0.5.dist-info/top_level.txt
memez-0.0.5.dist-info/RECORD
